<?xml version="1.0" encoding="utf-8"?>
<qroot>
<question>
<Title>Pyglet Importerror : cannot import name key</Title>
<Body>&lt;p&gt;So I&#x27;m trying to learn how to use pyglet, and have zero experience using any GLs or 3D-programs. I&#x27;m trying to open a window using pyglet and keep getting this error. I&#x27;ve heard that pyglet needs to switch up to 32 bit before it can work on snow leopard but I&#x27;m not quite sure if that is the exact problem. &lt;/p&gt;&lt;p&gt;Some System Info: Using Python 2.7, Enthought Canopy Interpreter, Terminal Python is Original Python 2.7 not Enthought Distribution. Mac OS 10.6.8 Snow Leopard. Pyglet is version that comes with latest Enthought Canopy free version.&lt;/p&gt;&lt;p&gt;Here is the error:&lt;/p&gt;&lt;pre&gt;&lt;code&gt;import pyglet    ...:     ...: win = pyglet.window.Window()    ...: ---------------------------------------------------------------------------ImportError                               Traceback (most recent call last)&amp;lt;ipython-input-13-c91a7ca30a2f&amp;gt; in &amp;lt;module&amp;gt;()      1 import pyglet      2 ----&amp;gt; 3 win = pyglet.window.Window()      4 /Users/lievbirman/Library/Enthought/Canopy_64bit/User/lib/python2.7/site-packages/pyglet  /__init__.pyc in __getattr__(self, name)    304     305             import_name = &#x27;pyglet.%s&#x27; % self._module_name--&amp;gt; 306             __import__(import_name)    307             module = sys.modules[import_name]    308             object.__setattr__(self, &#x27;_module&#x27;, module)/Users/lievbirman/Library/Enthought/Canopy_64bit/User/lib/python2.7/site-packages/pyglet/window/__init__.py in &amp;lt;module&amp;gt;()   1667     # Try to determine which platform to use.   1668     if sys.platform == &#x27;darwin&#x27;:-&amp;gt; 1669         from pyglet.window.carbon import CarbonPlatform, CarbonWindow   1670         _platform = CarbonPlatform()   1671         Window = CarbonWindow/Users/lievbirman/Library/Enthought/Canopy_64bit/User/lib/python2.7/site-packages/pyglet/window/carbon/__init__.py in &amp;lt;module&amp;gt;()     47 from pyglet.window import WindowException, Platform, Display, Screen,      48     BaseWindow, MouseCursor, DefaultMouseCursor, _PlatformEventHandler---&amp;gt; 49 from pyglet.window import key     50 from pyglet.window import mouse     51 from pyglet.window import eventImportError: cannot import name key &lt;/code&gt;&lt;/pre&gt;&lt;p&gt;My greatest thanks in advance to anyone that can shine some light on this issue.&lt;/p&gt;</Body>
<Tags>python,python-2.7,window,macos-carbon,pyglet</Tags>
</question>
<answer>
<Body>&lt;p&gt;Found the answer on another thread:&lt;a href=&quot;https://stackoverflow.com/questions/24311119/installing-pyglet-in-mac?rq=1&quot;&gt;Installing Pyglet in mac&lt;/a&gt;&lt;/p&gt;&lt;p&gt;Run 32-bit Python by doing this in the terminal:&lt;/p&gt;&lt;p&gt;defaults write com.apple.versioner.python Prefer-32-Bit -bool yes&lt;/p&gt;</Body>
</answer>
<answer>
<Body>&lt;p&gt;I just had the same problem and I just uninstalled pyglet first and then install it again using:&lt;/p&gt;&lt;blockquote&gt;  &lt;blockquote&gt;    &lt;p&gt;pip install hg+&lt;a href=&quot;https://pyglet.googlecode.com/hg/&quot; rel=&quot;nofollow&quot;&gt;https://pyglet.googlecode.com/hg/&lt;/a&gt;&lt;/p&gt;  &lt;/blockquote&gt;&lt;/blockquote&gt;&lt;p&gt;Before reinstalling it make sure you have mercurial installed as well&lt;/p&gt;</Body>
</answer>
</qroot>
