<?xml version="1.0" encoding="utf-8"?>
<qroot>
<question>
<Title>&#x27;u&#x27; at the beginning of output (Sqlite, Python)</Title>
<Body>&lt;p&gt;I&#x27;m really confused about the sqlite part, where I print out my database, because I keep getting an &#x27;u&#x27; at the beginning of every line, it doesn&#x27;t have &#x27; &#x27; around though, which I assume is not accepted as a string? This only happens on this one programme (I tested it on other as well).&lt;/p&gt;&lt;p&gt;I checked the code many times (it doesn&#x27;t appear in the database when I open it with &#x27;SQLite database browser&#x27;)&lt;/p&gt;&lt;p&gt;So this is the code:&lt;/p&gt;&lt;pre&gt;&lt;code&gt;#!/usr/bin/pythonimport sqlite3import osdef list_n_convert(way):    if way == &#x27;mov&#x27;:#movie search        output = os.popen(&quot;find &#x27;/home/fugo/&#x27; -name &#x27;*.mp4&#x27; -printf &#x27;%f\n&#x27;&quot;).read()    word = &#x27;&#x27;    lyst = []    for letter in output:        if letter != &#x27;\n&#x27;:            word += str(letter)        else:            lyst.append(word)            word = &#x27;&#x27;    return lyst#Loop to create entriesdef entry_maker(lyst, column):    for count in range(len(lyst)):        cur.execute(&quot;INSERT OR IGNORE INTO myliltable ({}) VALUES (?)&quot;.format(column), (lyst[count],))        con.commit()if __name__ == &#x27;__main__&#x27;:    #necessities for start-up of sql-lite    con = sqlite3.connect(&#x27;movie.db&#x27;)    cur = con.cursor()    #Create a table, if it&#x27;s non-existent    cur.execute(&#x27;CREATE TABLE IF NOT EXISTS myliltable (name TEXT PRIMARY KEY, cover TEXT, genre TEXT)&#x27;)    entry_maker(list_n_convert(&#x27;mov&#x27;), &#x27;name&#x27;)    cur.execute(&#x27;SELECT * FROM myliltable&#x27;)    for row in cur.fetchall():        print(row) #print each row in a line &amp;lt;--- &#x27;ERROR&#x27; happens here    cur.close()    con.close()&lt;/code&gt;&lt;/pre&gt;&lt;p&gt;This is what the output looks like:&lt;/p&gt;&lt;pre&gt;&lt;code&gt;(u&#x27;Umbra.mp4&#x27;, None, None)(u&#x27;xd.mp4&#x27;, None, None)(u&#x27;Nice.mp4&#x27;, None, None)(u&#x27;Haha.mp4&#x27;, None, None)&lt;/code&gt;&lt;/pre&gt;&lt;p&gt;I&#x27;ll explain what the programme does, maybe it helps to find the error:&lt;/p&gt;&lt;p&gt;The first function &#x27;list_n_convert&#x27; searches on my home folder for any files with the ending &#x27;.mp4&#x27; and then converts the result of the search into strings and adds them on a list.&lt;/p&gt;&lt;p&gt;The second one does entries into the database for each element in the list (each mp4 file). At the end I call the functions and let each row get printed out; this is where the error happens.&lt;/p&gt;</Body>
<Tags>python,sqlite</Tags>
</question>
<answer>
<Body>&lt;p&gt;The u&#x27; is basically syntax for &#x27;this is unicode&#x27;. Use &lt;code&gt;str()&lt;/code&gt; to get a string.&lt;/p&gt;&lt;p&gt;See: &lt;a href=&quot;https://docs.python.org/2.7/tutorial/introduction.html#unicode-strings&quot; rel=&quot;nofollow&quot;&gt;Unicode Strings on the python docs&lt;/a&gt;&lt;/p&gt;</Body>
</answer>
</qroot>
